setup.py
heuris/__init__.py
heuris/client.py
heuris/message.py
heuris.egg-info/PKG-INFO
heuris.egg-info/SOURCES.txt
heuris.egg-info/dependency_links.txt
heuris.egg-info/requires.txt
heuris.egg-info/top_level.txt