Metadata-Version: 1.0
Name: heuris
Version: 0.4.0
Summary: Python client for heuris
Home-page: https://github.com/heurisio/heuris-py
Author: Alex Young
Author-email: alex@heuris.io
License: Apache License, Version 2.0
Platform: UNKNOWN
